pyascec/__init__.py
pyascec/ascec.py
pyascec/atomic_charge.py
pyascec/atomic_mass.py
pyascec/cluster.py
pyascec/driver_cale.py
pyascec/fungeom.py
pyascec/rand0.py
pyascec-3.0.4.dist-info/LICENSE
pyascec-3.0.4.dist-info/METADATA
pyascec-3.0.4.dist-info/WHEEL
pyascec-3.0.4.dist-info/RECORD
