Metadata-Version: 2.1
Name: pyascec
Version: 3.0.4
Summary: This code explores the potential energy surface of atomic and molecular clusters using a modified Metropolis criterion and Markov chain. This Python implementation makes the workflow easier and more efficient.
Author: AndyDanian
Author-email: danianescobarv@gmail.com
Requires-Python: >=3.10,<4.0
Classifier: Programming Language :: Python :: 3
Classifier: Programming Language :: Python :: 3.10
Classifier: Programming Language :: Python :: 3.11
Classifier: Programming Language :: Python :: 3.12
Requires-Dist: requests (>=2.32.5,<3.0.0)
